typedobject/__init__.py
typedobject/_decorator.py
typedobject/_meta.py
typedobject/_object.py
typedobject-1.1.1.dist-info/LICENSE
typedobject-1.1.1.dist-info/METADATA
typedobject-1.1.1.dist-info/WHEEL
typedobject-1.1.1.dist-info/top_level.txt
typedobject-1.1.1.dist-info/RECORD
