Metadata-Version: 2.1
Name: typedobject
Version: 1.1.1
Summary: Define real, inheritable, and efficient Python classes using variable annotations
Home-page: https://github.com/avakar/typedobject
Author: Martin Vejnár
Author-email: vejnar.martin@gmail.com
License: 0BSD
Platform: UNKNOWN
Classifier: Programming Language :: Python :: 3.7
Classifier: Programming Language :: Python :: 3.8
Classifier: License :: OSI Approved :: BSD License
Classifier: Topic :: Software Development :: Libraries
